{
  "users": [
    {
      "name": "abdallah",
      "email": "asd@asd.com",
      "password": "asas",
      "confirmPassword": "asas",
      "gender": "1",
      "year": "2005",
      "month": "09",
      "day": "16",
      "passwordType": "password",
      "showText": "show",
      "isVerified": true,
      "agreeTerms": true,
      "id": 3
    },
    {
      "name": "ledo",
      "email": "ledo@gmail.com",
      "password": "assdas",
      "confirmPassword": "assdas",
      "gender": "1",
      "year": "2000",
      "month": "12",
      "day": "19",
      "roll": "free",
      "passwordType": "text",
      "showText": "hide",
      "isVerified": true,
      "agreeTerms": true,
      "id": 4
    },
    {
      "password": "asd",
      "email": "asd@sa.com",
      "id": 5
    },
    {
      "name": "abdallah ",
      "email": "abdallah@asda.com",
      "password": "asdfasdf",
      "confirmPassword": "asdfasdf",
      "gender": "1",
      "year": "2001",
      "month": "01",
      "day": "20",
      "roll": "free",
      "passwordType": "password",
      "showText": "show",
      "isVerified": true,
      "agreeTerms": true,
      "id": 6
    },
    {
      "name": "assdaasd",
      "email": "asd@asd.com",
      "gender": "1",
      "year": "2002",
      "month": "11",
      "day": "20",
      "roll": "free",
      "passwordType": "password",
      "showText": "show",
      "isVerified": true,
      "agreeTerms": true,
      "password": "asd",
      "confirmPassword": "asd",
      "id": 7
    },
    {
      "name": "assdaasd",
      "email": "asd@asd.com",
      "gender": "1",
      "year": "2002",
      "month": "11",
      "day": "20",
      "roll": "free",
      "passwordType": "password",
      "showText": "show",
      "isVerified": true,
      "agreeTerms": true,
      "password": "asd",
      "confirmPassword": "asd",
      "id": 8
    },
    {
      "name": "assdaasd",
      "email": "asd@asd.com",
      "gender": "1",
      "year": "2002",
      "month": "11",
      "day": "20",
      "roll": "free",
      "passwordType": "text",
      "showText": "hide",
      "isVerified": true,
      "agreeTerms": true,
      "password": "asdasdasd",
      "confirmPassword": "asdasdasd",
      "id": 9
    },
    {
      "name": "assdaasd",
      "email": "asd@asd.com",
      "gender": "1",
      "year": "2002",
      "month": "11",
      "day": "20",
      "roll": "free",
      "passwordType": "password",
      "showText": "show",
      "isVerified": true,
      "agreeTerms": true,
      "password": "qwwe",
      "confirmPassword": "qwwe",
      "id": 10
    },
    {
      "name": "assdaasd",
      "email": "asd@asd.com",
      "gender": "1",
      "year": "2002",
      "month": "11",
      "day": "20",
      "roll": "free",
      "passwordType": "password",
      "showText": "show",
      "isVerified": true,
      "agreeTerms": true,
      "password": "qwwe",
      "confirmPassword": "qwwe",
      "id": 11
    },
    {
      "name": "asd",
      "email": "assad@as.com",
      "gender": "1",
      "year": "2002",
      "month": "11",
      "day": "18",
      "roll": "free",
      "passwordType": "password",
      "showText": "show",
      "isVerified": true,
      "agreeTerms": true,
      "password": "asd",
      "confirmPassword": "asd",
      "id": 12
    },
    {
      "name": "SDas",
      "email": "swdo@test.com",
      "gender": "1",
      "year": "1999",
      "month": "11",
      "day": "16",
      "roll": "free",
      "passwordType": "password",
      "showText": "show",
      "isVerified": true,
      "agreeTerms": true,
      "password": "asasass",
      "confirmPassword": "asassas",
      "id": 13
    },
    {
      "name": "asdsa",
      "email": "asdas@sdf.o",
      "gender": "2",
      "year": "2002",
      "month": "11",
      "day": "17",
      "roll": "free",
      "passwordType": "password",
      "showText": "show",
      "isVerified": true,
      "agreeTerms": true,
      "password": "a",
      "confirmPassword": "a",
      "id": 14
    },
    {
      "name": "asd",
      "email": "as@gmail.cas",
      "gender": "1",
      "year": "1999",
      "month": "11",
      "day": "18",
      "roll": "free",
      "passwordType": "password",
      "showText": "show",
      "isVerified": true,
      "agreeTerms": true,
      "password": "a",
      "confirmPassword": "a",
      "id": 15
    },
    {
      "name": "asd",
      "email": "asdQW@asd.coasd",
      "gender": "1",
      "year": "1998",
      "month": "11",
      "day": "18",
      "roll": "free",
      "passwordType": "password",
      "showText": "show",
      "isVerified": true,
      "agreeTerms": true,
      "password": "a",
      "confirmPassword": "a",
      "id": 16
    },
    {
      "name": "zsda",
      "email": "abozoooz2014.aa@gmail.com",
      "gender": "1",
      "year": "1983",
      "month": "11",
      "day": "17",
      "roll": "free",
      "passwordType": "password",
      "showText": "show",
      "isVerified": true,
      "agreeTerms": true,
      "password": "asd",
      "confirmPassword": "asd",
      "id": 17
    }
  ]
}